{
  "albums": [
    {
      "id": "1",
      "name": "Amateur Skater",
      "release_date": "2025-01-01",
      "description": "Our latest EP about trying to stay radical while your joints tell you otherwise.",
      "spotify_url": "https://open.spotify.com/album/38AXd6UNJ3EDpUUZGx0ubE",
      "bandcamp_url": "https://alarmalarm.bandcamp.com/music",
      "image_url": "/src/assets/images/album-cover-ep2.jpg",
      "tracks": [
        {
          "name": "All By My Best Friend Bob, Again",
          "position": 1
        },
        {
          "name": "Esto Termina Aqui",
          "position": 2
        },
        {
          "name": "NOFX",
          "position": 3
        },
        {
          "name": "I'm not worried enough (Live)",
          "position": 4
        }
      ]
    },
    {
      "id": "2",
      "name": "98-99",
      "release_date": "2025-02-01",
      "description": "A melodic tribute to the era of baggy jeans, MSN Messenger, and the peak of 90s punk.",
      "spotify_url": "https://open.spotify.com/album/2bFikvFpFiMqFP8CmU2ttM",
      "bandcamp_url": "https://alarmalarm.bandcamp.com/music",
      "image_url": "/src/assets/images/album-cover-ep1.jpg",
      "tracks": [
        {
          "name": "Todo Sin Terminar",
          "position": 1
        },
        {
          "name": "Sprint Retrospective",
          "position": 2
        },
        {
          "name": "Banda Tributo",
          "position": 3
        },
        {
          "name": "Déjame En Paz (Live)",
          "position": 4
        }
      ]
    },
    {
      "id": "3",
      "name": "Whatever...",
      "release_date": "2022-01-01",
      "description": "A confirmation that, indeed, things haven't improved.",
      "spotify_url": "https://open.spotify.com/album/1cb5wJKrETBtXU5iauhmj2",
      "bandcamp_url": "https://alarmalarm.bandcamp.com/album/whatever",
      "image_url": "/src/assets/images/album-cover-lp2.jpg",
      "tracks": [
        {
          "name": "Git Init",
          "position": 1
        },
        {
          "name": "With Or Without You",
          "position": 2
        },
        {
          "name": "Punk Rock Scene",
          "position": 3
        },
        {
          "name": "I'm Not Alright'",
          "position": 4
        },
        {
          "name": "Pull Request",
          "position": 5
        },
        {
          "name": "Déjame En Paz",
          "position": 6
        },
        {
          "name": "Scheissegal",
          "position": 7
        },
        {
          "name": "I'm Not Worried Enough",
          "position": 8
        },
        {
          "name": "I'm Only Happy When I'm Angry",
          "position": 9
        },
        {
          "name": "Friday Night",
          "position": 10
        },
        {
          "name": "A Song To Leah",
          "position": 11
        }
      ]
    },
    {
      "id": "4",
      "name": "Bloody Hell!",
      "release_date": "2020-01-01",
      "description": "Our debut scream into the void, recorded at Hollers Analog Studio.",
      "spotify_url": "https://open.spotify.com/album/4SIJzb8ZWfxtvz6kjQlJe0",
      "bandcamp_url": "https://alarmalarm.bandcamp.com/album/bloody-hell",
      "image_url": "/src/assets/images/album-cover-lp1.jpg",
      "tracks": [
        {
          "name": "Hello World",
          "position": 1
        },
        {
          "name": "Office Hours",
          "position": 2
        },
        {
          "name": "Radio",
          "position": 3
        },
        {
          "name": "Saturday Night",
          "position": 4
        },
        {
          "name": "Midlife Crisis",
          "position": 5
        },
        {
          "name": "All You Can Eat",
          "position": 6
        },
        {
          "name": "Hass",
          "position": 7
        },
        {
          "name": "Summer Love",
          "position": 8
        },
        {
          "name": "Give Up",
          "position": 9
        },
        {
          "name": "No",
          "position": 10
        }
      ]
    }
  ],
  "gridItems": [
    {
      "id": "1",
      "image_url": "/src/assets/images/photo1.jpg",
      "caption": "Preparing new stuff! #bandlife #phototime #punk",
      "alt_description": "Alarm! Alarm! band members posing for a photo in a gritty urban setting."
    },
    {
      "id": "2",
      "image_url": "/src/assets/images/photo2.jpeg",
      "caption": "Thanks everyone! Almost 8K listeners! We love you! #spotify #punkrock #alarmalarm",
      "alt_description": "Alarm! Alarm! 2025 Spotify stats screenshot showing streams and listeners."
    }
  ]
}